fileUploadS3_x21182787/__init__.py
fileUploadS3_x21182787/uploadGenerateUrl.py
fileuploads3_x21182787-0.0.1.dist-info/METADATA
fileuploads3_x21182787-0.0.1.dist-info/WHEEL
fileuploads3_x21182787-0.0.1.dist-info/licenses/LICENSE
fileuploads3_x21182787-0.0.1.dist-info/RECORD
