Metadata-Version: 2.1
Name: fileUploadS3_x21182787
Version: 0.0.1
Summary: Package to upload object to aws s3 and return s3 file url
Project-URL: Homepage, https://github.com/abhishekmedhane/S3-FileUpload-UrlGen
Project-URL: repository, https://github.com/abhishekmedhane/S3-FileUpload-UrlGen
Author-email: Abhishek Medhane <abhishekmedhane04@gmail.com>
License-File: LICENSE
Classifier: License :: OSI Approved :: MIT License
Classifier: Operating System :: OS Independent
Classifier: Programming Language :: Python :: 3
Requires-Python: >=3.7
Requires-Dist: boto3
